landtransportsg/__init__.py
landtransportsg/author.py
landtransportsg/constants.py
landtransportsg/exceptions.py
landtransportsg/landtransportsg.py
landtransportsg/py.typed
landtransportsg/timezone.py
landtransportsg/types.py
landtransportsg/version.py
landtransportsg/active_mobility/__init__.py
landtransportsg/active_mobility/client.py
landtransportsg/active_mobility/constants.py
landtransportsg/active_mobility/types.py
landtransportsg/active_mobility/types_args.py
landtransportsg/electric_vehicle/__init__.py
landtransportsg/electric_vehicle/client.py
landtransportsg/electric_vehicle/constants.py
landtransportsg/electric_vehicle/types.py
landtransportsg/electric_vehicle/types_args.py
landtransportsg/geospatial/__init__.py
landtransportsg/geospatial/client.py
landtransportsg/geospatial/constants.py
landtransportsg/geospatial/types_args.py
landtransportsg/public_transport/__init__.py
landtransportsg/public_transport/client.py
landtransportsg/public_transport/constants.py
landtransportsg/public_transport/types.py
landtransportsg/public_transport/types_args.py
landtransportsg/traffic/__init__.py
landtransportsg/traffic/client.py
landtransportsg/traffic/constants.py
landtransportsg/traffic/types.py
landtransportsg-2.1.1.dist-info/licenses/LICENSE.txt
landtransportsg-2.1.1.dist-info/METADATA
landtransportsg-2.1.1.dist-info/WHEEL
landtransportsg-2.1.1.dist-info/top_level.txt
landtransportsg-2.1.1.dist-info/RECORD
