Metadata-Version: 2.4
Name: landtransportsg
Version: 2.1.1
Summary: Python package for interacting with APIs available at LTA DataMall
Author-email: Yuhui <yuhuibc@gmail.com>
Project-URL: Homepage, https://github.com/yuhui/landtransportsg
Project-URL: Documentation, https://landtransportsg.readthedocs.io/en/latest/
Project-URL: Repository, https://github.com/yuhui/landtransportsg.git
Project-URL: Bug Tracker, https://github.com/yuhui/landtransportsg/issues
Project-URL: Changelog, https://github.com/yuhui/landtransportsg/blob/master/CHANGELOG.rst
Keywords: lta,land transport authority,datamall,python,singapore,wrapper
Classifier: Development Status :: 5 - Production/Stable
Classifier: Environment :: Web Environment
Classifier: Intended Audience :: Developers
Classifier: Natural Language :: English
Classifier: Operating System :: MacOS :: MacOS X
Classifier: Operating System :: Microsoft :: Windows
Classifier: Operating System :: OS Independent
Classifier: Operating System :: POSIX
Classifier: Programming Language :: Python :: 3
Classifier: Topic :: Software Development :: Libraries :: Python Modules
Classifier: Typing :: Typed
Requires-Python: >=3.13
License-File: LICENSE.txt
Requires-Dist: requests
Requires-Dist: requests-cache
Requires-Dist: typeguard
Requires-Dist: types-requests
Dynamic: license-file
